<?xml version="1.0" encoding="UTF-8"?>
<products>
 <product>
  <productId>601489</productId>
  <productName>Soft Iced Wedding Cake - Vanilla Sponge (Fruit Top Tier) - 3 Tier - </productName>
  <productImage>http://d3l6n8hsebkot8.cloudfront.net/images/products/9/LN_601489_BP_9.jpg</productImage>
  <productUrl>http://www.waitrose.com/shop/DisplayProductFlyout?productId=85318&amp;?utm_source=infectious&amp;utm_medium=display&amp;utm_campaign=baby</productUrl>
  <price>155.00</price>
  <categoryid1>Entertaining</categoryid1>
  <categoryid2>Wedding Cakes</categoryid2>
  <categoryid3>Mixed Filling Wedding Cakes</categoryid3>
 </product>
 <product>
  <productId>722092</productId>
  <productName>Soft Iced Wedding Cake - Vanilla Sponge (Fruit Top Tier) - 2 Tier - </productName>
  <productImage>http://d1ycl3zewbvuig.cloudfront.net/images/products/9/LN_722092_BP_9.jpg</productImage>
  <productUrl>http://www.waitrose.com/shop/DisplayProductFlyout?productId=102607&amp;?utm_source=infectious&amp;utm_medium=display&amp;utm_campaign=baby</productUrl>
  <price>105.00</price>
  <categoryid1>Entertaining</categoryid1>
  <categoryid2>Wedding Cakes</categoryid2>
  <categoryid3>Mixed Filling Wedding Cakes</categoryid3>
 </product>
 <product>
  <productId>710016</productId>
  <productName>Ivory Lily &amp; Rose Sugar Flower Wedding Cake - Vanilla (Fruit Top Tier) - 3 Tier - </productName>
  <productImage>http://d25hqtnqp5nl24.cloudfront.net/images/products/9/LN_710016_BP_9.jpg</productImage>
  <productUrl>http://www.waitrose.com/shop/DisplayProductFlyout?productId=100859&amp;?utm_source=infectious&amp;utm_medium=display&amp;utm_campaign=baby</productUrl>
  <price>285.00</price>
  <categoryid1>Entertaining</categoryid1>
  <categoryid2>Wedding Cakes</categoryid2>
  <categoryid3>Mixed Filling Wedding Cakes</categoryid3>
 </product>
 <product>
  <productId>664461</productId>
  <productName>Polka Dots &amp; Roses Wedding Cake (Ivory &amp; Cream) - Fruit - 4 Tier - </productName>
  <productImage>http://duetogsaij514.cloudfront.net/images/products/9/LN_664461_BP_9.jpg</productImage>
  <productUrl>http://www.waitrose.com/shop/DisplayProductFlyout?productId=94339&amp;?utm_source=infectious&amp;utm_medium=display&amp;utm_campaign=baby</productUrl>
  <price>349.00</price>
  <categoryid1>Entertaining</categoryid1>
  <categoryid2>Wedding Cakes</categoryid2>
  <categoryid3>Wedding Cakes by Fiona Cairns</categoryid3>
 </product>
 <product>
  <productId>624379</productId>
  <productName>Ivory Lily &amp; Rose Sugar Flower Wedding Cake - Vanilla (Fruit Top Tier) - 2 Tier - </productName>
  <productImage>http://d25hqtnqp5nl24.cloudfront.net/images/products/9/LN_624379_BP_9.jpg</productImage>
  <productUrl>http://www.waitrose.com/shop/DisplayProductFlyout?productId=88574&amp;?utm_source=infectious&amp;utm_medium=display&amp;utm_campaign=baby</productUrl>
  <price>185.00</price>
  <categoryid1>Entertaining</categoryid1>
  <categoryid2>Wedding Cakes</categoryid2>
  <categoryid3>Mixed Filling Wedding Cakes</categoryid3>
 </product>
 <product>
  <productId>504886</productId>
  <productName>Fiona Cairns Vintage Fairytale 3-tier Wedding Cake (Mixed Filling) - </productName>
  <productImage>http://d25hqtnqp5nl24.cloudfront.net/images/products/9/LN_504886_BP_9.jpg</productImage>
  <productUrl>http://www.waitrose.com/shop/DisplayProductFlyout?productId=71295&amp;?utm_source=infectious&amp;utm_medium=display&amp;utm_campaign=baby</productUrl>
  <price>455.00</price>
  <categoryid1>Entertaining</categoryid1>
  <categoryid2>Wedding Cakes</categoryid2>
  <categoryid3>Wedding Cakes by Fiona Cairns</categoryid3>
 </product>
 <product>
  <productId>396958</productId>
  <productName>Rose &amp; Butterfly Wedding Cake (White) - Vanilla &amp; Fruit - 3 Tier - </productName>
  <productImage>http://d3l6n8hsebkot8.cloudfront.net/images/products/9/LN_396958_BP_9.jpg</productImage>
  <productUrl>http://www.waitrose.com/shop/DisplayProductFlyout?productId=55793&amp;?utm_source=infectious&amp;utm_medium=display&amp;utm_campaign=baby</productUrl>
  <price>239.00</price>
  <categoryid1>Entertaining</categoryid1>
  <categoryid2>Wedding Cakes</categoryid2>
  <categoryid3>Mixed Filling Wedding Cakes</categoryid3>
 </product>
 <product>
  <productId>682494</productId>
  <productName>Polka Dots &amp; Roses Wedding Cake (Ivory &amp; Cream) - 2 Tier Fruit, 2 Tier Chocolate - </productName>
  <productImage>http://duetogsaij514.cloudfront.net/images/products/9/LN_682494_BP_9.jpg</productImage>
  <productUrl>http://www.waitrose.com/shop/DisplayProductFlyout?productId=96947&amp;?utm_source=infectious&amp;utm_medium=display&amp;utm_campaign=baby</productUrl>
  <price>335.00</price>
  <categoryid1>Entertaining</categoryid1>
  <categoryid2>Wedding Cakes</categoryid2>
  <categoryid3>Wedding Cakes by Fiona Cairns</categoryid3>
 </product>
 <product>
  <productId>463196</productId>
  <productName>Rose &amp; Butterfly Wedding Cake (White) - Vanilla (Raised Fruit Top Tier) - 3 Tier - </productName>
  <productImage>http://d25hqtnqp5nl24.cloudfront.net/images/products/9/LN_463196_BP_9.jpg</productImage>
  <productUrl>http://www.waitrose.com/shop/DisplayProductFlyout?productId=65281&amp;?utm_source=infectious&amp;utm_medium=display&amp;utm_campaign=baby</productUrl>
  <price>244.00</price>
  <categoryid1>Entertaining</categoryid1>
  <categoryid2>Wedding Cakes</categoryid2>
  <categoryid3>Mixed Filling Wedding Cakes</categoryid3>
 </product>
 <product>
  <productId>453881</productId>
  <productName>Fiona Cains Pink &amp; White Polka Dots &amp; Roses 4-tier Wedding Cake (Sponge &amp; Fruit) - </productName>
  <productImage>http://d25hqtnqp5nl24.cloudfront.net/images/products/9/LN_453881_BP_9.jpg</productImage>
  <productUrl>http://www.waitrose.com/shop/DisplayProductFlyout?productId=63932&amp;?utm_source=infectious&amp;utm_medium=display&amp;utm_campaign=baby</productUrl>
  <price>335.00</price>
  <categoryid1>Entertaining</categoryid1>
  <categoryid2>Wedding Cakes</categoryid2>
  <categoryid3>Mixed Filling Wedding Cakes</categoryid3>
 </product>
 <product>
  <productId>474182</productId>
  <productName>Rose &amp; Butterfly Wedding Cake (White &amp; Pink) - Fruit &amp; Vanilla - 3 Tier - </productName>
  <productImage>http://d1ycl3zewbvuig.cloudfront.net/images/products/9/LN_474182_BP_9.jpg</productImage>
  <productUrl>http://www.waitrose.com/shop/DisplayProductFlyout?productId=140736&amp;?utm_source=infectious&amp;utm_medium=display&amp;utm_campaign=baby</productUrl>
  <price>239.00</price>
  <categoryid1>Entertaining</categoryid1>
  <categoryid2>Wedding Cakes</categoryid2>
  <categoryid3>Mixed Filling Wedding Cakes</categoryid3>
 </product>
 <product>
  <productId>387848</productId>
  <productName>Fiona Cairns Pink &amp; White Polka Dots &amp; Roses 4-tier Wedding Cake (Chocolate &amp; Fruit) - </productName>
  <productImage>http://d3l6n8hsebkot8.cloudfront.net/images/products/9/LN_387848_BP_9.jpg</productImage>
  <productUrl>http://www.waitrose.com/shop/DisplayProductFlyout?productId=54501&amp;?utm_source=infectious&amp;utm_medium=display&amp;utm_campaign=baby</productUrl>
  <price>335.00</price>
  <categoryid1>Entertaining</categoryid1>
  <categoryid2>Wedding Cakes</categoryid2>
  <categoryid3>Mixed Filling Wedding Cakes</categoryid3>
 </product>
 <product>
  <productId>400066</productId>
  <productName>Ivory Lily &amp; Rose Sugar Flower Wedding Cake - Fruit - Medium - </productName>
  <productImage>http://d1ycl3zewbvuig.cloudfront.net/images/products/9/LN_400066_BP_9.jpg</productImage>
  <productUrl>http://www.waitrose.com/shop/DisplayProductFlyout?productId=56278&amp;?utm_source=infectious&amp;utm_medium=display&amp;utm_campaign=baby</productUrl>
  <price>99.00</price>
  <categoryid1>Entertaining</categoryid1>
  <categoryid2>Wedding Cakes</categoryid2>
  <categoryid3>Fruit Wedding Cakes</categoryid3>
 </product>
 <product>
  <productId>585281</productId>
  <productName>Ivory Lily &amp; Rose Sugar Flower Wedding Cake - Fruit - Small - </productName>
  <productImage>http://d25hqtnqp5nl24.cloudfront.net/images/products/9/LN_585281_BP_9.jpg</productImage>
  <productUrl>http://www.waitrose.com/shop/DisplayProductFlyout?productId=82961&amp;?utm_source=infectious&amp;utm_medium=display&amp;utm_campaign=baby</productUrl>
  <price>67.00</price>
  <categoryid1>Entertaining</categoryid1>
  <categoryid2>Wedding Cakes</categoryid2>
  <categoryid3>Fruit Wedding Cakes</categoryid3>
 </product>
 <product>
  <productId>572494</productId>
  <productName>Fiona Cairns Ivory Rose Petal 3-tier Wedding Cake (Fruit) - </productName>
  <productImage>http://d25hqtnqp5nl24.cloudfront.net/images/products/9/LN_572494_BP_9.jpg</productImage>
  <productUrl>http://www.waitrose.com/shop/DisplayProductFlyout?productId=81111&amp;?utm_source=infectious&amp;utm_medium=display&amp;utm_campaign=baby</productUrl>
  <price>315.00</price>
  <categoryid1>Entertaining</categoryid1>
  <categoryid2>Wedding Cakes</categoryid2>
  <categoryid3>Wedding Cakes by Fiona Cairns</categoryid3>
 </product>
 <product>
  <productId>714657</productId>
  <productName>Rose &amp; Butterfly Wedding Cake (White &amp; Pink) - Fruit (Raised Top Tier) - 3 Tier - </productName>
  <productDescription>A rich fruit cake covered with almond paste and soft white icing, with a pink middle tier. Sugar roses and wired trailing leaves decorate the cake, and each tier is finished with a sugar butterfly. This raised top tier cake is assembled with its tiers aligned centrally. (15, 20, 25cm diameter)To order a wedding cake up to 1 year in advance, please call 0800 169 2701 or visit your nearest branch.</productDescription>
  <productImage>http://d3l6n8hsebkot8.cloudfront.net/images/products/9/LN_714657_BP_9.jpg</productImage>
  <productUrl>http://www.waitrose.com/shop/DisplayProductFlyout?productId=140911&amp;?utm_source=infectious&amp;utm_medium=display&amp;utm_campaign=baby</productUrl>
  <price>259.00</price>
  <categoryid1>Entertaining</categoryid1>
  <categoryid2>Wedding Cakes</categoryid2>
  <categoryid3>Fruit Wedding Cakes</categoryid3>
 </product>
 <product>
  <productId>037649</productId>
  <productName>Soft Iced Wedding Cake - Fruit - 3 Tier - </productName>
  <productImage>http://d25hqtnqp5nl24.cloudfront.net/images/products/9/LN_037649_BP_9.jpg</productImage>
  <productUrl>http://www.waitrose.com/shop/DisplayProductFlyout?productId=18789&amp;?utm_source=infectious&amp;utm_medium=display&amp;utm_campaign=baby</productUrl>
  <price>175.00</price>
  <categoryid1>Entertaining</categoryid1>
  <categoryid2>Wedding Cakes</categoryid2>
  <categoryid3>Fruit Wedding Cakes</categoryid3>
 </product>
 <product>
  <productId>646297</productId>
  <productName>Rose &amp; Butterfly Wedding Cake (White) - Fruit (Raised Top Tier) - 3 Tier - </productName>
  <productImage>http://d3l6n8hsebkot8.cloudfront.net/images/products/9/LN_646297_BP_9.jpg</productImage>
  <productUrl>http://www.waitrose.com/shop/DisplayProductFlyout?productId=91718&amp;?utm_source=infectious&amp;utm_medium=display&amp;utm_campaign=baby</productUrl>
  <price>259.00</price>
  <categoryid1>Entertaining</categoryid1>
  <categoryid2>Wedding Cakes</categoryid2>
  <categoryid3>Fruit Wedding Cakes</categoryid3>
 </product>
 <product>
  <productId>766671</productId>
  <productName>Fiona Cairns Vintage Fairytale 3-tier Wedding Cake (Fruit) - </productName>
  <productImage>http://duetogsaij514.cloudfront.net/images/products/9/LN_766671_BP_9.jpg</productImage>
  <productUrl>http://www.waitrose.com/shop/DisplayProductFlyout?productId=109023&amp;?utm_source=infectious&amp;utm_medium=display&amp;utm_campaign=baby</productUrl>
  <price>485.00</price>
  <categoryid1>Entertaining</categoryid1>
  <categoryid2>Wedding Cakes</categoryid2>
  <categoryid3>Wedding Cakes by Fiona Cairns</categoryid3>
 </product>
 <product>
  <productId>761972</productId>
  <productName>Ivory Lily &amp; Rose Sugar Flower Wedding Cake - Fruit - Large - </productName>
  <productImage>http://d1ycl3zewbvuig.cloudfront.net/images/products/9/LN_761972_BP_9.jpg</productImage>
  <productUrl>http://www.waitrose.com/shop/DisplayProductFlyout?productId=108363&amp;?utm_source=infectious&amp;utm_medium=display&amp;utm_campaign=baby</productUrl>
  <price>130.00</price>
  <categoryid1>Entertaining</categoryid1>
  <categoryid2>Wedding Cakes</categoryid2>
  <categoryid3>Fruit Wedding Cakes</categoryid3>
 </product>
 <product>
  <productId>490792</productId>
  <productName>Soft Iced Wedding Cake - Fruit - 2 Tier - </productName>
  <productImage>http://d25hqtnqp5nl24.cloudfront.net/images/products/9/LN_490792_BP_9.jpg</productImage>
  <productUrl>http://www.waitrose.com/shop/DisplayProductFlyout?productId=69349&amp;?utm_source=infectious&amp;utm_medium=display&amp;utm_campaign=baby</productUrl>
  <price>115.00</price>
  <categoryid1>Entertaining</categoryid1>
  <categoryid2>Wedding Cakes</categoryid2>
  <categoryid3>Fruit Wedding Cakes</categoryid3>
 </product>
 <product>
  <productId>476839</productId>
  <productName>Ivory Lily &amp; Rose Sugar Flower Wedding Cake - Fruit - 3 Tier - </productName>
  <productImage>http://duetogsaij514.cloudfront.net/images/products/9/LN_476839_BP_9.jpg</productImage>
  <productUrl>http://www.waitrose.com/shop/DisplayProductFlyout?productId=67284&amp;?utm_source=infectious&amp;utm_medium=display&amp;utm_campaign=baby</productUrl>
  <price>299.00</price>
  <categoryid1>Entertaining</categoryid1>
  <categoryid2>Wedding Cakes</categoryid2>
  <categoryid3>Fruit Wedding Cakes</categoryid3>
 </product>
 <product>
  <productId>470958</productId>
  <productName>Ivory Lily &amp; Rose Sugar Flower Wedding Cake - Fruit - 2 Tier - </productName>
  <productImage>http://duetogsaij514.cloudfront.net/images/products/9/LN_470958_BP_9.jpg</productImage>
  <productUrl>http://www.waitrose.com/shop/DisplayProductFlyout?productId=66407&amp;?utm_source=infectious&amp;utm_medium=display&amp;utm_campaign=baby</productUrl>
  <price>195.00</price>
  <categoryid1>Entertaining</categoryid1>
  <categoryid2>Wedding Cakes</categoryid2>
  <categoryid3>Fruit Wedding Cakes</categoryid3>
 </product>
 <product>
  <productId>612258</productId>
  <productName>Fiona Cairns Flame Rose Petal 3-tier Wedding Cake (Fruit) - </productName>
  <productImage>http://d3l6n8hsebkot8.cloudfront.net/images/products/9/LN_612258_BP_9.jpg</productImage>
  <productUrl>http://www.waitrose.com/shop/DisplayProductFlyout?productId=86859&amp;?utm_source=infectious&amp;utm_medium=display&amp;utm_campaign=baby</productUrl>
  <price>315.00</price>
  <categoryid1>Entertaining</categoryid1>
  <categoryid2>Wedding Cakes</categoryid2>
  <categoryid3>Fruit Wedding Cakes</categoryid3>
 </product>
 <product>
  <productId>512584</productId>
  <productName>Rose &amp; Butterfly Wedding Cake (White &amp; Pink) - Fruit - 3 Tier - </productName>
  <productDescription>A rich fruit cake covered with almond paste and soft white icing, with a pink middle tier. Sugar roses and wired trailing leaves decorate the cake, and each tier is finished with a sugar butterfly. This 3 tier cake is stacked off-centre, to allow space for the decoration.To order a wedding cake up to 1 year in advance, please call 0800 169 2701 or visit your nearest branch.</productDescription>
  <productImage>http://d25hqtnqp5nl24.cloudfront.net/images/products/9/LN_512584_BP_9.jpg</productImage>
  <productUrl>http://www.waitrose.com/shop/DisplayProductFlyout?productId=140769&amp;?utm_source=infectious&amp;utm_medium=display&amp;utm_campaign=baby</productUrl>
  <price>249.00</price>
  <categoryid1>Entertaining</categoryid1>
  <categoryid2>Wedding Cakes</categoryid2>
  <categoryid3>Fruit Wedding Cakes</categoryid3>
 </product>
 <product>
  <productId>654280</productId>
  <productName>Fiona Cairns Ivory Rose Petal 3-tier Wedding Cake (Sponge) - </productName>
  <productImage>http://d25hqtnqp5nl24.cloudfront.net/images/products/9/LN_654280_BP_9.jpg</productImage>
  <productUrl>http://www.waitrose.com/shop/DisplayProductFlyout?productId=92889&amp;?utm_source=infectious&amp;utm_medium=display&amp;utm_campaign=baby</productUrl>
  <price>295.00</price>
  <categoryid1>Entertaining</categoryid1>
  <categoryid2>Wedding Cakes</categoryid2>
  <categoryid3>Wedding Cakes by Fiona Cairns</categoryid3>
 </product>
 <product>
  <productId>630499</productId>
  <productName>Fiona Cains Pink &amp; White Polka Dots &amp; Roses 4-tier Wedding Cake (Fruit) - </productName>
  <productImage>http://d25hqtnqp5nl24.cloudfront.net/images/products/9/LN_630499_BP_9.jpg</productImage>
  <productUrl>http://www.waitrose.com/shop/DisplayProductFlyout?productId=89563&amp;?utm_source=infectious&amp;utm_medium=display&amp;utm_campaign=baby</productUrl>
  <price>349.00</price>
  <categoryid1>Entertaining</categoryid1>
  <categoryid2>Wedding Cakes</categoryid2>
  <categoryid3>Fruit Wedding Cakes</categoryid3>
 </product>
 <product>
  <productId>527456</productId>
  <productName>Fiona Cairns Pastel Rose Petal 3-tier Wedding Cake (Fruit) - </productName>
  <productImage>http://d25hqtnqp5nl24.cloudfront.net/images/products/9/LN_527456_BP_9.jpg</productImage>
  <productUrl>http://www.waitrose.com/shop/DisplayProductFlyout?productId=74570&amp;?utm_source=infectious&amp;utm_medium=display&amp;utm_campaign=baby</productUrl>
  <price>315.00</price>
  <categoryid1>Entertaining</categoryid1>
  <categoryid2>Wedding Cakes</categoryid2>
  <categoryid3>Wedding Cakes by Fiona Cairns</categoryid3>
 </product>
 <product>
  <productId>407993</productId>
  <productName>Rose &amp; Butterfly Wedding Cake (White) - Fruit - 3 Tier - </productName>
  <productImage>http://d1ycl3zewbvuig.cloudfront.net/images/products/9/LN_407993_BP_9.jpg</productImage>
  <productUrl>http://www.waitrose.com/shop/DisplayProductFlyout?productId=57418&amp;?utm_source=infectious&amp;utm_medium=display&amp;utm_campaign=baby</productUrl>
  <price>249.00</price>
  <categoryid1>Entertaining</categoryid1>
  <categoryid2>Wedding Cakes</categoryid2>
  <categoryid3>Fruit Wedding Cakes</categoryid3>
 </product>
 <product>
  <productId>492581</productId>
  <productName>Fiona Cairns Vintage Fairytale Carousel Cake (Fruit) - </productName>
  <productImage>http://d25hqtnqp5nl24.cloudfront.net/images/products/9/LN_492581_BP_9.jpg</productImage>
  <productUrl>http://www.waitrose.com/shop/DisplayProductFlyout?productId=69601&amp;?utm_source=infectious&amp;utm_medium=display&amp;utm_campaign=baby</productUrl>
  <price>230.00</price>
  <categoryid1>Entertaining</categoryid1>
  <categoryid2>Wedding Cakes</categoryid2>
  <categoryid3>Fruit Wedding Cakes</categoryid3>
 </product>
 <product>
  <productId>591494</productId>
  <productName>Ivory Lily &amp; Rose Sugar Flower Wedding Cake - Vanilla - 2 Tier - </productName>
  <productImage>http://d1ycl3zewbvuig.cloudfront.net/images/products/9/LN_591494_BP_9.jpg</productImage>
  <productUrl>http://www.waitrose.com/shop/DisplayProductFlyout?productId=83816&amp;?utm_source=infectious&amp;utm_medium=display&amp;utm_campaign=baby</productUrl>
  <price>185.00</price>
  <categoryid1>Entertaining</categoryid1>
  <categoryid2>Wedding Cakes</categoryid2>
  <categoryid3>Vanilla Sponge Wedding Cakes</categoryid3>
 </product>
 <product>
  <productId>568476</productId>
  <productName>Soft Iced Wedding Cake - Vanilla Sponge - 3 Tier - </productName>
  <productImage>http://d1ycl3zewbvuig.cloudfront.net/images/products/9/LN_568476_BP_9.jpg</productImage>
  <productUrl>http://www.waitrose.com/shop/DisplayProductFlyout?productId=80516&amp;?utm_source=infectious&amp;utm_medium=display&amp;utm_campaign=baby</productUrl>
  <price>155.00</price>
  <categoryid1>Entertaining</categoryid1>
  <categoryid2>Wedding Cakes</categoryid2>
  <categoryid3>Vanilla Sponge Wedding Cakes</categoryid3>
 </product>
 <product>
  <productId>754802</productId>
  <productName>Ivory Lily &amp; Rose Sugar Flower Wedding Cake - Vanilla - Medium - </productName>
  <productImage>http://d1ycl3zewbvuig.cloudfront.net/images/products/9/LN_754802_BP_9.jpg</productImage>
  <productUrl>http://www.waitrose.com/shop/DisplayProductFlyout?productId=107355&amp;?utm_source=infectious&amp;utm_medium=display&amp;utm_campaign=baby</productUrl>
  <price>95.00</price>
  <categoryid1>Entertaining</categoryid1>
  <categoryid2>Wedding Cakes</categoryid2>
  <categoryid3>Vanilla Sponge Wedding Cakes</categoryid3>
 </product>
 <product>
  <productId>750638</productId>
  <productName>Rose &amp; Butterfly Wedding Cake (White) - Vanilla (Raised Top Tier) - 3 Tier - </productName>
  <productImage>http://d25hqtnqp5nl24.cloudfront.net/images/products/9/LN_750638_BP_9.jpg</productImage>
  <productUrl>http://www.waitrose.com/shop/DisplayProductFlyout?productId=106772&amp;?utm_source=infectious&amp;utm_medium=display&amp;utm_campaign=baby</productUrl>
  <price>244.00</price>
  <categoryid1>Entertaining</categoryid1>
  <categoryid2>Wedding Cakes</categoryid2>
  <categoryid3>Vanilla Sponge Wedding Cakes</categoryid3>
 </product>
 <product>
  <productId>796804</productId>
  <productName>Soft Iced Wedding Cake - Vanilla Sponge - 2 Tier - </productName>
  <productImage>http://d3l6n8hsebkot8.cloudfront.net/images/products/9/LN_796804_BP_9.jpg</productImage>
  <productUrl>http://www.waitrose.com/shop/DisplayProductFlyout?productId=113382&amp;?utm_source=infectious&amp;utm_medium=display&amp;utm_campaign=baby</productUrl>
  <price>105.00</price>
  <categoryid1>Entertaining</categoryid1>
  <categoryid2>Wedding Cakes</categoryid2>
  <categoryid3>Vanilla Sponge Wedding Cakes</categoryid3>
 </product>
 <product>
  <productId>522065</productId>
  <productName>Ivory Lily &amp; Rose Sugar Flower Wedding Cake - Vanilla - 3 Tier - </productName>
  <productImage>http://d3l6n8hsebkot8.cloudfront.net/images/products/9/LN_522065_BP_9.jpg</productImage>
  <productUrl>http://www.waitrose.com/shop/DisplayProductFlyout?productId=73832&amp;?utm_source=infectious&amp;utm_medium=display&amp;utm_campaign=baby</productUrl>
  <price>285.00</price>
  <categoryid1>Entertaining</categoryid1>
  <categoryid2>Wedding Cakes</categoryid2>
  <categoryid3>Vanilla Sponge Wedding Cakes</categoryid3>
 </product>
 <product>
  <productId>413664</productId>
  <productName>Fiona Cairns Pastel Rose Petal 3-tier Wedding Cake (Sponge) - </productName>
  <productImage>http://d3l6n8hsebkot8.cloudfront.net/images/products/9/LN_413664_BP_9.jpg</productImage>
  <productUrl>http://www.waitrose.com/shop/DisplayProductFlyout?productId=58206&amp;?utm_source=infectious&amp;utm_medium=display&amp;utm_campaign=baby</productUrl>
  <price>295.00</price>
  <categoryid1>Entertaining</categoryid1>
  <categoryid2>Wedding Cakes</categoryid2>
  <categoryid3>Wedding Cakes by Fiona Cairns</categoryid3>
 </product>
 <product>
  <productId>503685</productId>
  <productName>Ivory Lily &amp; Rose Sugar Flower Wedding Cake - Vanilla - Large - </productName>
  <productImage>http://duetogsaij514.cloudfront.net/images/products/9/LN_503685_BP_9.jpg</productImage>
  <productUrl>http://www.waitrose.com/shop/DisplayProductFlyout?productId=71142&amp;?utm_source=infectious&amp;utm_medium=display&amp;utm_campaign=baby</productUrl>
  <price>120.00</price>
  <categoryid1>Entertaining</categoryid1>
  <categoryid2>Wedding Cakes</categoryid2>
  <categoryid3>Vanilla Sponge Wedding Cakes</categoryid3>
 </product>
 <product>
  <productId>466620</productId>
  <productName>Fiona Cains Pink &amp; White Polka Dots &amp; Roses 4-tier Wedding Cake (Sponge) - </productName>
  <productImage>http://d3l6n8hsebkot8.cloudfront.net/images/products/9/LN_466620_BP_9.jpg</productImage>
  <productUrl>http://www.waitrose.com/shop/DisplayProductFlyout?productId=65757&amp;?utm_source=infectious&amp;utm_medium=display&amp;utm_campaign=baby</productUrl>
  <price>319.00</price>
  <categoryid1>Entertaining</categoryid1>
  <categoryid2>Wedding Cakes</categoryid2>
  <categoryid3>Vanilla Sponge Wedding Cakes</categoryid3>
 </product>
 <product>
  <productId>604493</productId>
  <productName>Rose &amp; Butterfly Wedding Cake (White) - Vanilla - 3 Tier - </productName>
  <productImage>http://d1ycl3zewbvuig.cloudfront.net/images/products/9/LN_604493_BP_9.jpg</productImage>
  <productUrl>http://www.waitrose.com/shop/DisplayProductFlyout?productId=85739&amp;?utm_source=infectious&amp;utm_medium=display&amp;utm_campaign=baby</productUrl>
  <price>233.00</price>
  <categoryid1>Entertaining</categoryid1>
  <categoryid2>Wedding Cakes</categoryid2>
  <categoryid3>Vanilla Sponge Wedding Cakes</categoryid3>
 </product>
 <product>
  <productId>588977</productId>
  <productName>Rose &amp; Butterfly Wedding Cake (White &amp; Pink) - Vanilla - 3 Tier - </productName>
  <productDescription>A vanilla sponge filled with raspberry jam and buttercream, covered with almond paste and soft white icing, with a pink middle tier. Sugar roses and wired trailing leaves decorate the cake, and each tier is finished with a sugar butterfly. This 3 tier cake is stacked off-centre, to allow space for the decoration.To order a wedding cake up to 1 year in advance, please call 0800 169 2701 or visit your nearest branch.</productDescription>
  <productImage>http://d3l6n8hsebkot8.cloudfront.net/images/products/9/LN_588977_BP_9.jpg</productImage>
  <productUrl>http://www.waitrose.com/shop/DisplayProductFlyout?productId=140839&amp;?utm_source=infectious&amp;utm_medium=display&amp;utm_campaign=baby</productUrl>
  <price>233.00</price>
  <categoryid1>Entertaining</categoryid1>
  <categoryid2>Wedding Cakes</categoryid2>
  <categoryid3>Vanilla Sponge Wedding Cakes</categoryid3>
 </product>
 <product>
  <productId>472977</productId>
  <productName>Rose &amp; Butterfly Wedding Cake (White &amp; Pink) - Vanilla (Raised Fruit Top Tier) - 3 Tier - </productName>
  <productImage>http://d1ycl3zewbvuig.cloudfront.net/images/products/9/LN_472977_BP_9.jpg</productImage>
  <productUrl>http://www.waitrose.com/shop/DisplayProductFlyout?productId=140734&amp;?utm_source=infectious&amp;utm_medium=display&amp;utm_campaign=baby</productUrl>
  <price>244.00</price>
  <categoryid1>Entertaining</categoryid1>
  <categoryid2>Wedding Cakes</categoryid2>
  <categoryid3>Vanilla Sponge Wedding Cakes</categoryid3>
 </product>
 <product>
  <productId>462743</productId>
  <productName>Rose &amp; Butterfly Wedding Cake (White &amp; Pink) - Vanilla (Raised Top Tier) - 3 Tier - </productName>
  <productDescription>A vanilla sponge filled with raspberry jam and buttercream, covered with almond paste and soft white icing, with a green middle tier. Sugar roses and wired trailing leaves decorate the cake, and each tier is finished with a sugar butterfly. This raised top tier cake is assembled with its tiers aligned centrally. (15, 20, 25cm diameter)To order a wedding cake up to 1 year in advance, please call 0800 169 2701 or visit your nearest branch.</productDescription>
  <productImage>http://d1ycl3zewbvuig.cloudfront.net/images/products/9/LN_462743_BP_9.jpg</productImage>
  <productUrl>http://www.waitrose.com/shop/DisplayProductFlyout?productId=140727&amp;?utm_source=infectious&amp;utm_medium=display&amp;utm_campaign=baby</productUrl>
  <price>244.00</price>
  <categoryid1>Entertaining</categoryid1>
  <categoryid2>Wedding Cakes</categoryid2>
  <categoryid3>Vanilla Sponge Wedding Cakes</categoryid3>
 </product>
 <product>
  <productId>700727</productId>
  <productName>Ivory Lily &amp; Rose Sugar Flower Wedding Cake - Vanilla - Small - </productName>
  <productImage>http://duetogsaij514.cloudfront.net/images/products/9/LN_700727_BP_9.jpg</productImage>
  <productUrl>http://www.waitrose.com/shop/DisplayProductFlyout?productId=99458&amp;?utm_source=infectious&amp;utm_medium=display&amp;utm_campaign=baby</productUrl>
  <price>64.00</price>
  <categoryid1>Entertaining</categoryid1>
  <categoryid2>Wedding Cakes</categoryid2>
  <categoryid3>Vanilla Sponge Wedding Cakes</categoryid3>
 </product>
 <product>
  <productId>477402</productId>
  <productName>Fiona Cairns Flame Rose Petal 3-tier Wedding Cake (Sponge) - </productName>
  <productImage>http://d3l6n8hsebkot8.cloudfront.net/images/products/9/LN_477402_BP_9.jpg</productImage>
  <productUrl>http://www.waitrose.com/shop/DisplayProductFlyout?productId=67362&amp;?utm_source=infectious&amp;utm_medium=display&amp;utm_campaign=baby</productUrl>
  <price>295.00</price>
  <categoryid1>Entertaining</categoryid1>
  <categoryid2>Wedding Cakes</categoryid2>
  <categoryid3>Vanilla Sponge Wedding Cakes</categoryid3>
 </product>
 <product>
  <productId>539416</productId>
  <productName>Fiona Cains Pink &amp; White Polka Dots &amp; Roses 4-tier Wedding Cake (Chocolate) - </productName>
  <productImage>http://d3l6n8hsebkot8.cloudfront.net/images/products/9/LN_539416_BP_9.jpg</productImage>
  <productUrl>http://www.waitrose.com/shop/DisplayProductFlyout?productId=76274&amp;?utm_source=infectious&amp;utm_medium=display&amp;utm_campaign=baby</productUrl>
  <price>319.00</price>
  <categoryid1>Entertaining</categoryid1>
  <categoryid2>Wedding Cakes</categoryid2>
  <categoryid3>Chocolate Wedding Cakes</categoryid3>
 </product>
 <product>
  <productId>367302</productId>
  <productName>Polka Dots &amp; Roses Wedding Cake (Ivory &amp; Cream) - Chocolate - 4 Tier - </productName>
  <productImage>http://d25hqtnqp5nl24.cloudfront.net/images/products/9/LN_367302_BP_9.jpg</productImage>
  <productUrl>http://www.waitrose.com/shop/DisplayProductFlyout?productId=51644&amp;?utm_source=infectious&amp;utm_medium=display&amp;utm_campaign=baby</productUrl>
  <price>319.00</price>
  <categoryid1>Entertaining</categoryid1>
  <categoryid2>Wedding Cakes</categoryid2>
  <categoryid3>Wedding Cakes by Fiona Cairns</categoryid3>
 </product>
 <product>
  <productId>034343</productId>
  <productName>Chocolate Wedding Cake - Gold - 3 Tier - </productName>
  <productImage>http://duetogsaij514.cloudfront.net/images/products/9/LN_034343_BP_9.jpg</productImage>
  <productUrl>http://www.waitrose.com/shop/DisplayProductFlyout?productId=17223&amp;?utm_source=infectious&amp;utm_medium=display&amp;utm_campaign=baby</productUrl>
  <price>239.00</price>
  <categoryid1>Entertaining</categoryid1>
  <categoryid2>Wedding Cakes</categoryid2>
  <categoryid3>Contemporary Wedding Cakes</categoryid3>
 </product>
 <product>
  <productId>048490</productId>
  <productName>Chocolate Wedding Cake - Gold - Medium - </productName>
  <productImage>http://d25hqtnqp5nl24.cloudfront.net/images/products/9/LN_048490_BP_9.jpg</productImage>
  <productUrl>http://www.waitrose.com/shop/DisplayProductFlyout?productId=24070&amp;?utm_source=infectious&amp;utm_medium=display&amp;utm_campaign=baby</productUrl>
  <price>82.00</price>
  <categoryid1>Entertaining</categoryid1>
  <categoryid2>Wedding Cakes</categoryid2>
  <categoryid3>Contemporary Wedding Cakes</categoryid3>
 </product>
 <product>
  <productId>004386</productId>
  <productName>Chocolate Wedding Cake - Gold - Large - </productName>
  <productImage>http://d25hqtnqp5nl24.cloudfront.net/images/products/9/LN_004386_BP_9.jpg</productImage>
  <productUrl>http://www.waitrose.com/shop/DisplayProductFlyout?productId=1819&amp;?utm_source=infectious&amp;utm_medium=display&amp;utm_campaign=baby</productUrl>
  <price>109.00</price>
  <categoryid1>Entertaining</categoryid1>
  <categoryid2>Wedding Cakes</categoryid2>
  <categoryid3>Contemporary Wedding Cakes</categoryid3>
 </product>
 <product>
  <productId>020396</productId>
  <productName>Chocolate Wedding Cake - Gold - Small - </productName>
  <productImage>http://d3l6n8hsebkot8.cloudfront.net/images/products/9/LN_020396_BP_9.jpg</productImage>
  <productUrl>http://www.waitrose.com/shop/DisplayProductFlyout?productId=9921&amp;?utm_source=infectious&amp;utm_medium=display&amp;utm_campaign=baby</productUrl>
  <price>49.00</price>
  <categoryid1>Entertaining</categoryid1>
  <categoryid2>Wedding Cakes</categoryid2>
  <categoryid3>Contemporary Wedding Cakes</categoryid3>
 </product>
 <product>
  <productId>488302</productId>
  <productName>Chocolate Wedding Cake - Gold - 2 Tier - </productName>
  <productImage>http://d25hqtnqp5nl24.cloudfront.net/images/products/9/LN_488302_BP_9.jpg</productImage>
  <productUrl>http://www.waitrose.com/shop/DisplayProductFlyout?productId=68987&amp;?utm_source=infectious&amp;utm_medium=display&amp;utm_campaign=baby</productUrl>
  <price>159.00</price>
  <categoryid1>Entertaining</categoryid1>
  <categoryid2>Wedding Cakes</categoryid2>
  <categoryid3>Contemporary Wedding Cakes</categoryid3>
 </product>
 <product>
  <productId>419913</productId>
  <productName>Chocolate Polka Dots &amp; Roses Wedding Cake - </productName>
  <productImage>http://duetogsaij514.cloudfront.net/images/products/9/LN_419913_BP_9.jpg</productImage>
  <productUrl>http://www.waitrose.com/shop/DisplayProductFlyout?productId=196020&amp;?utm_source=infectious&amp;utm_medium=display&amp;utm_campaign=baby</productUrl>
  <price>190.00</price>
  <categoryid1>Entertaining</categoryid1>
  <categoryid2>Wedding Cakes</categoryid2>
  <categoryid3>Contemporary Wedding Cakes</categoryid3>
 </product>
 <product>
  <productId>515809</productId>
  <productName>Fiona Cairns Vintage Fairytale Carousel Cake (Chocolate) - </productName>
  <productImage>http://d3l6n8hsebkot8.cloudfront.net/images/products/9/LN_515809_BP_9.jpg</productImage>
  <productUrl>http://www.waitrose.com/shop/DisplayProductFlyout?productId=140773&amp;?utm_source=infectious&amp;utm_medium=display&amp;utm_campaign=baby</productUrl>
  <price>229.00</price>
  <categoryid1>Entertaining</categoryid1>
  <categoryid2>Wedding Cakes</categoryid2>
  <categoryid3>Chocolate Wedding Cakes</categoryid3>
 </product>
 <product>
  <productId>072597</productId>
  <productName>White Chocolate Wedding Cake - Plain - 3 Tier - </productName>
  <productImage>http://d3l6n8hsebkot8.cloudfront.net/images/products/9/LN_072597_BP_9.jpg</productImage>
  <productUrl>http://www.waitrose.com/shop/DisplayProductFlyout?productId=36852&amp;?utm_source=infectious&amp;utm_medium=display&amp;utm_campaign=baby</productUrl>
  <price>225.00</price>
  <categoryid1>Entertaining</categoryid1>
  <categoryid2>Wedding Cakes</categoryid2>
  <categoryid3>Chocolate Wedding Cakes</categoryid3>
 </product>
 <product>
  <productId>423214</productId>
  <productName>White Chocolate Wedding Cake - Brown Spotted Ribbon - 3 Tier - </productName>
  <productImage>http://d1ycl3zewbvuig.cloudfront.net/images/products/9/LN_423214_BP_9.jpg</productImage>
  <productUrl>http://www.waitrose.com/shop/DisplayProductFlyout?productId=59526&amp;?utm_source=infectious&amp;utm_medium=display&amp;utm_campaign=baby</productUrl>
  <price>259.00</price>
  <categoryid1>Entertaining</categoryid1>
  <categoryid2>Wedding Cakes</categoryid2>
  <categoryid3>Chocolate Wedding Cakes</categoryid3>
 </product>
 <product>
  <productId>699044</productId>
  <productName>White Chocolate Wedding Cake - Plain - Raised 3 Tier - </productName>
  <productImage>http://d1ycl3zewbvuig.cloudfront.net/images/products/9/LN_699044_BP_9.jpg</productImage>
  <productUrl>http://www.waitrose.com/shop/DisplayProductFlyout?productId=99249&amp;?utm_source=infectious&amp;utm_medium=display&amp;utm_campaign=baby</productUrl>
  <price>259.00</price>
  <categoryid1>Entertaining</categoryid1>
  <categoryid2>Wedding Cakes</categoryid2>
  <categoryid3>Chocolate Wedding Cakes</categoryid3>
 </product>
 <product>
  <productId>597076</productId>
  <productName>Fiona Cairns Vintage Fairytale Carousel Cake (Chocolate) - </productName>
  <productImage>http://d3l6n8hsebkot8.cloudfront.net/images/products/9/LN_597076_BP_9.jpg</productImage>
  <productUrl>http://www.waitrose.com/shop/DisplayProductFlyout?productId=84636&amp;?utm_source=infectious&amp;utm_medium=display&amp;utm_campaign=baby</productUrl>
  <price>210.00</price>
  <categoryid1>Entertaining</categoryid1>
  <categoryid2>Wedding Cakes</categoryid2>
  <categoryid3>Chocolate Wedding Cakes</categoryid3>
 </product>
 <product>
  <productId>048534</productId>
  <productName>White Chocolate Wedding Cake - Ivory - 3 Tier - </productName>
  <productImage>http://d3l6n8hsebkot8.cloudfront.net/images/products/9/LN_048534_BP_9.jpg</productImage>
  <productUrl>http://www.waitrose.com/shop/DisplayProductFlyout?productId=24102&amp;?utm_source=infectious&amp;utm_medium=display&amp;utm_campaign=baby</productUrl>
  <price>259.00</price>
  <categoryid1>Entertaining</categoryid1>
  <categoryid2>Wedding Cakes</categoryid2>
  <categoryid3>Chocolate Wedding Cakes</categoryid3>
 </product>
</products>
